{
  "date": "2025-04-10",
  "changes": [
    {
      "fileName": "Sys_uttils.py",
      "timestamp": "2025-04-10T05:37:25.269Z",
      "changeType": "modified",
      "linesChanged": 20,
      "fileType": "py"
    },
    {
      "fileName": "Sys_uttils.py",
      "timestamp": "2025-04-10T05:38:21.449Z",
      "changeType": "modified",
      "linesChanged": 20,
      "fileType": "py"
    },
    {
      "fileName": "Docker_python.py",
      "timestamp": "2025-04-10T06:03:14.690Z",
      "changeType": "created",
      "linesChanged": 1,
      "fileType": "py"
    },
    {
      "fileName": "Docker_python.py",
      "timestamp": "2025-04-10T06:03:22.866Z",
      "changeType": "modified",
      "linesChanged": 1,
      "fileType": "py"
    },
    {
      "fileName": "Docker_python.py",
      "timestamp": "2025-04-10T06:03:45.339Z",
      "changeType": "modified",
      "linesChanged": 2,
      "fileType": "py"
    },
    {
      "fileName": "Docker_python.py",
      "timestamp": "2025-04-10T06:03:45.591Z",
      "changeType": "modified",
      "linesChanged": 2,
      "fileType": "py"
    },
    {
      "fileName": "Docker_python.py",
      "timestamp": "2025-04-10T06:04:10.601Z",
      "changeType": "modified",
      "linesChanged": 2,
      "fileType": "py"
    },
    {
      "fileName": "Docker_python.py",
      "timestamp": "2025-04-10T06:04:10.797Z",
      "changeType": "modified",
      "linesChanged": 2,
      "fileType": "py"
    },
    {
      "fileName": "Docker_python.py",
      "timestamp": "2025-04-10T06:05:21.606Z",
      "changeType": "modified",
      "linesChanged": 10,
      "fileType": "py"
    },
    {
      "fileName": "Docker_python.py",
      "timestamp": "2025-04-10T06:05:29.475Z",
      "changeType": "modified",
      "linesChanged": 10,
      "fileType": "py"
    },
    {
      "fileName": "Docker_python.py",
      "timestamp": "2025-04-10T06:05:31.082Z",
      "changeType": "modified",
      "linesChanged": 10,
      "fileType": "py"
    }
  ],
  "totalChanges": 11,
  "startTime": "2025-04-10T05:36:09.109Z",
  "endTime": "2025-04-10T06:05:31.085Z",
  "projectName": "c:\\Users\\suhel\\OneDrive\\Desktop\\Python for Automation",
  "branchName": "master"
}